moydomjkh/__init__.py
moydomjkh/account.py
moydomjkh/command_line.py
moydomjkh/exceptions.py
moydomjkh/meter.py
moydomjkh/period.py
moydomjkh/session.py
moydomjkh/user.py
moydomjkh-0.0.3.dist-info/LICENSE.txt
moydomjkh-0.0.3.dist-info/METADATA
moydomjkh-0.0.3.dist-info/WHEEL
moydomjkh-0.0.3.dist-info/entry_points.txt
moydomjkh-0.0.3.dist-info/top_level.txt
moydomjkh-0.0.3.dist-info/RECORD
