Metadata-Version: 2.1
Name: moydomjkh
Version: 0.0.3
Summary: api для работы с порталом https://newlk.erconline.ru/
Home-page: https://github.com/yusinv/moydomjkh
Author: @yusinv
Author-email: yusinv@gmail.com
License: MIT
Keywords: moydomjkh
Classifier: Development Status :: 3 - Alpha
Classifier: Intended Audience :: Developers
Classifier: Topic :: Software Development :: Build Tools
Classifier: License :: OSI Approved :: MIT License
Classifier: Programming Language :: Python :: 3
Classifier: Programming Language :: Python :: 3.4
Classifier: Programming Language :: Python :: 3.5
Classifier: Programming Language :: Python :: 3.6
Classifier: Programming Language :: Python :: 3.7
Classifier: Programming Language :: Python :: 3.8
Classifier: Programming Language :: Python :: 3.9
License-File: LICENSE.txt
Requires-Dist: requests
Requires-Dist: argparse
